span_to_ibo/__init__.py
span_to_ibo/doccano.py
span_to_ibo-0.1.0.dist-info/LICENSE
span_to_ibo-0.1.0.dist-info/METADATA
span_to_ibo-0.1.0.dist-info/WHEEL
span_to_ibo-0.1.0.dist-info/RECORD
