Metadata-Version: 2.1
Name: span-to-ibo
Version: 0.1.0
Summary: This is a script to convert the output file of doccano to a format that is easy to handle with sklearn-crfsuite.
Home-page: https://github.com/inoueakimitsu/span-to-ibo
Author: Akimitsu Inoue
Author-email: inoue.akimitsu@gmail.com
Requires-Python: >=3.9,<4.0
Classifier: Programming Language :: Python :: 3
Classifier: Programming Language :: Python :: 3.9
Classifier: Programming Language :: Python :: 3.10
Classifier: Programming Language :: Python :: 3.11
Requires-Dist: janome (>=0.4.2,<0.5.0)
Requires-Dist: pandas (>=1.5.3,<2.0.0)
Project-URL: Repository, https://github.com/inoueakimitsu/span-to-ibo
